expense_csv_generator_pkg/__init__.py
expense_csv_generator_pkg/expense_csv.py
expensecsvgenerator-0.0.1.dist-info/LICENSE
expensecsvgenerator-0.0.1.dist-info/METADATA
expensecsvgenerator-0.0.1.dist-info/WHEEL
expensecsvgenerator-0.0.1.dist-info/top_level.txt
expensecsvgenerator-0.0.1.dist-info/RECORD
