Metadata-Version: 2.1
Name: expensecsvgenerator
Version: 0.0.1
Summary: Download your expense in form of csv based on the selected date range.
Home-page: https://github.com/pypa/sampleproject
Author: Vyom Vora
Author-email: workforce2060@gmail.com
License: UNKNOWN
Platform: UNKNOWN
Classifier: Programming Language :: Python :: 3
Classifier: License :: OSI Approved :: MIT License
Classifier: Operating System :: OS Independent
Requires-Python: >=3.6
License-File: LICENSE
